randomus/__init__.py
randomus-1.0.0.dist-info/LICENSE
randomus-1.0.0.dist-info/METADATA
randomus-1.0.0.dist-info/WHEEL
randomus-1.0.0.dist-info/top_level.txt
randomus-1.0.0.dist-info/RECORD
